clang/__init__.py
clang/cindex.py
clang-20.1.5.dist-info/METADATA
clang-20.1.5.dist-info/WHEEL
clang-20.1.5.dist-info/licenses/LICENSE.TXT
clang-20.1.5.dist-info/RECORD
