Metadata-Version: 2.2
Name: clang
Version: 20.1.5
Summary: libclang python bindings
Keywords: llvm,clang,libclang
Author: LLVM team - pypi upload by Loic Jaquemet
License: Apache-2.0 with LLVM exception
Classifier: Intended Audience :: Developers
Classifier: License :: OSI Approved :: Apache Software License
Classifier: Development Status :: 5 - Production/Stable
Classifier: Topic :: Software Development :: Compilers
Classifier: Programming Language :: Python :: 3
Project-URL: Homepage, http://clang.llvm.org/
Project-URL: Download, http://llvm.org/releases/download.html
